pubkeeper/server/core/auth/local/__init__.py
pubkeeper/server/core/auth/local/alembic.ini
pubkeeper/server/core/auth/local/db.py
pubkeeper/server/core/auth/local/module.py
pubkeeper/server/core/auth/local/provider.py
pubkeeper/server/core/auth/local/alembic/README
pubkeeper/server/core/auth/local/alembic/env.py
pubkeeper/server/core/auth/local/alembic/script.py.mako
pubkeeper/server/core/auth/local/alembic/versions/f04d0cdb7469_initial.py
pubkeeper/server/core/auth/local/handlers/__init__.py
pubkeeper/server/core/auth/local/handlers/auth.py
pubkeeper/server/core/auth/local/handlers/base.py
pubkeeper/server/core/auth/local/handlers/token.py
pubkeeper/server/core/auth/local/handlers/user.py
pubkeeper/server/core/auth/local/handlers/validate.py
pubkeeper/server/core/auth/local/handlers/web.py
pubkeeper/server/core/auth/local/models/__init__.py
pubkeeper/server/core/auth/local/models/base.py
pubkeeper/server/core/auth/local/models/right.py
pubkeeper/server/core/auth/local/models/token.py
pubkeeper/server/core/auth/local/models/user.py
pubkeeper/server/core/auth/local/site/README.md
pubkeeper/server/core/auth/local/site/asset-manifest.json
pubkeeper/server/core/auth/local/site/favicon.ico
pubkeeper/server/core/auth/local/site/index.html
pubkeeper/server/core/auth/local/site/manifest.json
pubkeeper/server/core/auth/local/site/fonts/lato/LatoLatin-Black.eot
pubkeeper/server/core/auth/local/site/fonts/lato/LatoLatin-Black.ttf
pubkeeper/server/core/auth/local/site/fonts/lato/LatoLatin-Black.woff
pubkeeper/server/core/auth/local/site/fonts/lato/LatoLatin-Black.woff2
pubkeeper/server/core/auth/local/site/fonts/lato/LatoLatin-BlackItalic.eot
pubkeeper/server/core/auth/local/site/fonts/lato/LatoLatin-BlackItalic.ttf
pubkeeper/server/core/auth/local/site/fonts/lato/LatoLatin-BlackItalic.woff
pubkeeper/server/core/auth/local/site/fonts/lato/LatoLatin-BlackItalic.woff2
pubkeeper/server/core/auth/local/site/fonts/lato/LatoLatin-Bold.eot
pubkeeper.server.core.auth.local-1.1.11.dist-info/DESCRIPTION.rst
pubkeeper.server.core.auth.local-1.1.11.dist-info/METADATA
pubkeeper.server.core.auth.local-1.1.11.dist-info/RECORD
pubkeeper.server.core.auth.local-1.1.11.dist-info/WHEEL
pubkeeper.server.core.auth.local-1.1.11.dist-info/metadata.json
pubkeeper.server.core.auth.local-1.1.11.dist-info/top_level.txt
