Metadata-Version: 2.0
Name: pubkeeper.server.core.auth.local
Version: 1.1.11
Summary: Simple database backed token authority for Pubkeeper
Home-page: http://github.com/pubkeeper/python-server-core-auth-local
Author: n.io
Author-email: info@n.io
License: UNKNOWN
Keywords: pubkeeper,python-server-core,python-server-core-auth-local
Platform: UNKNOWN
Classifier: License :: Other/Proprietary License
Classifier: Programming Language :: Python :: 3
Classifier: Programming Language :: Python :: 3.5
Requires-Dist: pubkeeper.server.core (~=1.1)
Requires-Dist: pyjwt (~=1.5.0)
Requires-Dist: sqlalchemy (~=1.2.0)
Requires-Dist: alembic (~=0.9.9)
Requires-Dist: psycopg2 (~=2.7.4)
